[{"gender":"male","name":{"title":"Mr","first":"Peter-Michael","last":"Ferber"},"location":{"street":{"number":3679,"name":"Goethestraße"},"city":"Schwabmünchen","state":"Baden-Württemberg","country":"Germany","postcode":75667,"coordinates":{"latitude":"-47.2634","longitude":"-102.9131"},"timezone":{"offset":"-3:00","description":"Brazil, Buenos Aires, Georgetown"}},"email":"peter-michael.ferber@example.com","login":{"uuid":"c3555c0b-ddb3-4ab0-a093-af2a95ab5908","username":"organicduck685","password":"1986","salt":"12RmPSbA","md5":"7b24d2c21f37b29c3dc1cc0bcb72ca52","sha1":"f7180164824364a209633bbd70b84ba4c732297b","sha256":"6bf55e7f6a6331e6cdf8c7b17a787805e65966ae3dca18f8e8d52ef1bbb2c0a7"},"dob":{"date":"1995-07-06T06:18:11.341Z","age":25},"registered":{"date":"2005-03-27T12:49:10.053Z","age":15},"phone":"0636-7360565","cell":"0178-8303304","id":{"name":"","value":null},"picture":{"large":"https://randomuser.me/api/portraits/men/68.jpg","medium":"https://randomuser.me/api/portraits/med/men/68.jpg","thumbnail":"https://randomuser.me/api/portraits/thumb/men/68.jpg"},"nat":"DE"},{"gender":"male","name":{"title":"Mr","first":"Roope","last":"Korpi"},"location":{"street":{"number":1236,"name":"Hatanpään Valtatie"},"city":"Lahti","state":"Tavastia Proper","country":"Finland","postcode":38461,"coordinates":{"latitude":"26.9934","longitude":"12.8034"},"timezone":{"offset":"+10:00","description":"Eastern Australia, Guam, Vladivostok"}},"email":"roope.korpi@example.com","login":{"uuid":"dd505517-73c5-4f12-ad52-8874c556cabc","username":"silverostrich754","password":"gryphon","salt":"jHFDsUvv","md5":"a01015d17977c4dcc297f5f5a0a4c33c","sha1":"ae13e07ec9003615e656f395dc0e0c2e3b859577","sha256":"127f6c3f50a3fb1fa04c70bab413f3ae57b5063f89f76257ecadd5867fd4cdb2"},"dob":{"date":"1986-04-22T18:32:55.582Z","age":34},"registered":{"date":"2015-11-19T20:17:32.232Z","age":5},"phone":"09-803-705","cell":"041-469-69-53","id":{"name":"HETU","value":"NaNNA821undefined"},"picture":{"large":"https://randomuser.me/api/portraits/men/84.jpg","medium":"https://randomuser.me/api/portraits/med/men/84.jpg","thumbnail":"https://randomuser.me/api/portraits/thumb/men/84.jpg"},"nat":"FI"},{"gender":"female","name":{"title":"Mrs","first":"Ella","last":"Leppo"},"location":{"street":{"number":9787,"name":"Pirkankatu"},"city":"Riihimäki","state":"Pirkanmaa","country":"Finland","postcode":84029,"coordinates":{"latitude":"50.4398","longitude":"124.3395"},"timezone":{"offset":"+10:00","description":"Eastern Australia, Guam, Vladivostok"}},"email":"ella.leppo@example.com","login":{"uuid":"ed05c092-6af9-4f86-9337-f287ff8b8d21","username":"biggorilla897","password":"wannabe","salt":"jgDFTXAM","md5":"02fdf34643fcec2a0abd548f26ce20e4","sha1":"07d20733b996b6fc06adc6d844f2ccf2be74e3ae","sha256":"454696376b2b6af157d381b0646fb170b9b62a629f7bef02df62a24b70eb3d1b"},"dob":{"date":"1981-09-02T20:57:29.232Z","age":39},"registered":{"date":"2014-07-29T12:49:44.206Z","age":6},"phone":"03-298-000","cell":"048-540-68-71","id":{"name":"HETU","value":"NaNNA618undefined"},"picture":{"large":"https://randomuser.me/api/portraits/women/18.jpg","medium":"https://randomuser.me/api/portraits/med/women/18.jpg","thumbnail":"https://randomuser.me/api/portraits/thumb/women/18.jpg"},"nat":"FI"},{"gender":"male","name":{"title":"Mr","first":"Francis","last":"Lawrence"},"location":{"street":{"number":2806,"name":"Richmond Park"},"city":"Nenagh","state":"Fingal","country":"Ireland","postcode":25075,"coordinates":{"latitude":"-5.5350","longitude":"1.3133"},"timezone":{"offset":"-8:00","description":"Pacific Time (US & Canada)"}},"email":"francis.lawrence@example.com","login":{"uuid":"bc69f16e-ab32-44fd-900d-870adb292da4","username":"bigduck397","password":"iceman1","salt":"trBrUH9B","md5":"86dbf9f965a02e0e77203e7922072842","sha1":"f6ab98f2139d2573865b2da74d4964204fa2f169","sha256":"ecb766c9d05eea667faf7f9cd89b22a038f7cdd8b51becedc5e2d8320bacbc26"},"dob":{"date":"1962-01-25T21:57:14.994Z","age":58},"registered":{"date":"2003-03-29T01:33:02.383Z","age":17},"phone":"031-765-1907","cell":"081-230-9220","id":{"name":"PPS","value":"4973433T"},"picture":{"large":"https://randomuser.me/api/portraits/men/78.jpg","medium":"https://randomuser.me/api/portraits/med/men/78.jpg","thumbnail":"https://randomuser.me/api/portraits/thumb/men/78.jpg"},"nat":"IE"},{"gender":"male","name":{"title":"Mr","first":"مهراد","last":"سالاری"},"location":{"street":{"number":8063,"name":"برادران حسنی"},"city":"یزد","state":"خوزستان","country":"Iran","postcode":96399,"coordinates":{"latitude":"-28.9189","longitude":"7.3511"},"timezone":{"offset":"+9:00","description":"Tokyo, Seoul, Osaka, Sapporo, Yakutsk"}},"email":"mhrd.slry@example.com","login":{"uuid":"24ab4254-74b8-4f77-9355-0c5cb93e1b44","username":"whitekoala366","password":"000007","salt":"nJ0HLhcW","md5":"401a3536ab41d7efbb3cb34274eaad4c","sha1":"bff10bee6f14d2193e93e138b4cc3e55b9e5a164","sha256":"03b8419e27f25aaf935a0e1a099811f8dec105020a753621d37b7c1a889b89e9"},"dob":{"date":"1947-08-09T04:35:19.648Z","age":73},"registered":{"date":"2009-01-17T14:38:23.619Z","age":11},"phone":"033-89640426","cell":"0974-009-7102","id":{"name":"","value":null},"picture":{"large":"https://randomuser.me/api/portraits/men/59.jpg","medium":"https://randomuser.me/api/portraits/med/men/59.jpg","thumbnail":"https://randomuser.me/api/portraits/thumb/men/59.jpg"},"nat":"IR"},{"gender":"male","name":{"title":"Mr","first":"Ryder","last":"Walker"},"location":{"street":{"number":8954,"name":"Frederick Street"},"city":"Auckland","state":"Taranaki","country":"New Zealand","postcode":93604,"coordinates":{"latitude":"-87.0129","longitude":"167.6367"},"timezone":{"offset":"-8:00","description":"Pacific Time (US & Canada)"}},"email":"ryder.walker@example.com","login":{"uuid":"3306fc57-55a7-4d4e-82f6-f39f8910c0f7","username":"orangepanda500","password":"sophie1","salt":"SOzNsXqw","md5":"5a9531b02280ee63dc08085ffa2fd8e7","sha1":"b1aee84f0c0b710d659d0279a4bda5d7a061757d","sha256":"b51ff40ddf493d143edcdd834e1fb7dc84627af1539758b44cdb2ebea69aac02"},"dob":{"date":"1969-12-23T21:09:51.411Z","age":51},"registered":{"date":"2015-11-27T18:22:34.569Z","age":5},"phone":"(595)-231-5952","cell":"(519)-112-9941","id":{"name":"","value":null},"picture":{"large":"https://randomuser.me/api/portraits/men/0.jpg","medium":"https://randomuser.me/api/portraits/med/men/0.jpg","thumbnail":"https://randomuser.me/api/portraits/thumb/men/0.jpg"},"nat":"NZ"},{"gender":"female","name":{"title":"Ms","first":"Anneke","last":"Hafner"},"location":{"street":{"number":6186,"name":"Industriestraße"},"city":"Heilsbronn","state":"Hessen","country":"Germany","postcode":58593,"coordinates":{"latitude":"-36.6904","longitude":"-160.3513"},"timezone":{"offset":"-2:00","description":"Mid-Atlantic"}},"email":"anneke.hafner@example.com","login":{"uuid":"6965efa6-074a-4c70-8fb3-04d7ec2e40be","username":"crazyrabbit572","password":"beaner","salt":"SaBP2025","md5":"c2413bbe94c4348411d56cece028f035","sha1":"0e7ce9b1cb64f472e9dc32349cbf5b6bc7a17f6c","sha256":"52eeecd56d2bc2bdcede4e17441f62738e5e1059b720ebded2908548fc487f7b"},"dob":{"date":"1959-11-28T15:33:44.302Z","age":61},"registered":{"date":"2002-09-27T13:57:11.425Z","age":18},"phone":"0565-7669701","cell":"0173-2899726","id":{"name":"","value":null},"picture":{"large":"https://randomuser.me/api/portraits/women/90.jpg","medium":"https://randomuser.me/api/portraits/med/women/90.jpg","thumbnail":"https://randomuser.me/api/portraits/thumb/women/90.jpg"},"nat":"DE"},{"gender":"male","name":{"title":"Mr","first":"Mikael","last":"Hatala"},"location":{"street":{"number":398,"name":"Reijolankatu"},"city":"Jämijärvi","state":"Åland","country":"Finland","postcode":23637,"coordinates":{"latitude":"38.3577","longitude":"54.5472"},"timezone":{"offset":"0:00","description":"Western Europe Time, London, Lisbon, Casablanca"}},"email":"mikael.hatala@example.com","login":{"uuid":"6a4c45d8-b77c-409f-8352-9f8482f114ee","username":"yellowgoose939","password":"newyear","salt":"yRlRiJ2L","md5":"442586db3a09a680d0825bee525332a4","sha1":"72c963e2d92f98193dba1f3617058682c882946e","sha256":"b0e351952338b137af37f5d82e22d5c6ddeb6b365366c91fb0c0a4c29790a1be"},"dob":{"date":"1950-10-31T15:08:57.276Z","age":70},"registered":{"date":"2017-04-06T17:07:18.459Z","age":3},"phone":"08-109-305","cell":"045-988-16-55","id":{"name":"HETU","value":"NaNNA245undefined"},"picture":{"large":"https://randomuser.me/api/portraits/men/93.jpg","medium":"https://randomuser.me/api/portraits/med/men/93.jpg","thumbnail":"https://randomuser.me/api/portraits/thumb/men/93.jpg"},"nat":"FI"},{"gender":"male","name":{"title":"Mr","first":"Dwight","last":"Herrera"},"location":{"street":{"number":9447,"name":"Queen Street"},"city":"Manchester","state":"Buckinghamshire","country":"United Kingdom","postcode":"QP1 3UG","coordinates":{"latitude":"-13.9671","longitude":"-117.2468"},"timezone":{"offset":"-3:30","description":"Newfoundland"}},"email":"dwight.herrera@example.com","login":{"uuid":"4814b697-568b-407a-9fde-14c840e998ba","username":"greenfish136","password":"bozo","salt":"G7MJZdZ9","md5":"2811ca7817862c59baedbb5253f2e8bc","sha1":"94fbb12f5de5085bba34cc740db1f8725ce89a45","sha256":"0f841a57669ed321b06cc962d67d4b7fd52cbc3b136722de645527e2da3f1c28"},"dob":{"date":"1963-02-21T17:32:31.926Z","age":57},"registered":{"date":"2016-09-01T17:30:05.483Z","age":4},"phone":"015395 94003","cell":"0720-080-720","id":{"name":"NINO","value":"ZA 15 88 26 P"},"picture":{"large":"https://randomuser.me/api/portraits/men/85.jpg","medium":"https://randomuser.me/api/portraits/med/men/85.jpg","thumbnail":"https://randomuser.me/api/portraits/thumb/men/85.jpg"},"nat":"GB"},{"gender":"male","name":{"title":"Mr","first":"Vero","last":"Santos"},"location":{"street":{"number":8502,"name":"Rua José Bonifácio "},"city":"Patos","state":"Tocantins","country":"Brazil","postcode":37498,"coordinates":{"latitude":"20.9943","longitude":"151.3696"},"timezone":{"offset":"-6:00","description":"Central Time (US & Canada), Mexico City"}},"email":"vero.santos@example.com","login":{"uuid":"b0354eff-b4a7-4392-b0b3-f26b3b29d9af","username":"brownwolf625","password":"bossman","salt":"UPG5yNCX","md5":"6d3db45a51bb5aecbcf7d88a6a00f8da","sha1":"4f8daa9439e69c2f3ca995862c648e031adbb3dc","sha256":"582352c42626396ba72ff1f9010e80ed638e610742f1ed36669c3a1aadc5784d"},"dob":{"date":"1971-03-12T16:42:14.404Z","age":49},"registered":{"date":"2002-09-14T21:47:56.927Z","age":18},"phone":"(22) 5739-0739","cell":"(46) 9712-9135","id":{"name":"","value":null},"picture":{"large":"https://randomuser.me/api/portraits/men/0.jpg","medium":"https://randomuser.me/api/portraits/med/men/0.jpg","thumbnail":"https://randomuser.me/api/portraits/thumb/men/0.jpg"},"nat":"BR"},{"gender":"female","name":{"title":"Mrs","first":"Sara","last":"Phillips"},"location":{"street":{"number":2003,"name":"Mill Lane"},"city":"Worcester","state":"Kent","country":"United Kingdom","postcode":"GK34 9AY","coordinates":{"latitude":"-27.0790","longitude":"155.6238"},"timezone":{"offset":"+4:00","description":"Abu Dhabi, Muscat, Baku, Tbilisi"}},"email":"sara.phillips@example.com","login":{"uuid":"1ded21e6-089e-4de2-a883-7695465fa80f","username":"tinylion523","password":"finally","salt":"uR5V9H1g","md5":"2eec52bfa00c5b231df5127838b42037","sha1":"aa16c5c7d1d530e1d1bf05bb50b87e638551d8d8","sha256":"4eae08371e7e8339e4fc79900696945cf1566ea350e83dd7faf71440ade7ed26"},"dob":{"date":"1987-10-31T16:42:29.021Z","age":33},"registered":{"date":"2007-05-09T20:23:03.390Z","age":13},"phone":"017687 19721","cell":"0738-302-981","id":{"name":"NINO","value":"ZB 19 16 77 E"},"picture":{"large":"https://randomuser.me/api/portraits/women/43.jpg","medium":"https://randomuser.me/api/portraits/med/women/43.jpg","thumbnail":"https://randomuser.me/api/portraits/thumb/women/43.jpg"},"nat":"GB"},{"gender":"female","name":{"title":"Ms","first":"Susie","last":"Smith"},"location":{"street":{"number":947,"name":"Richmond Park"},"city":"Mullingar","state":"Cork","country":"Ireland","postcode":77285,"coordinates":{"latitude":"4.5338","longitude":"157.5037"},"timezone":{"offset":"0:00","description":"Western Europe Time, London, Lisbon, Casablanca"}},"email":"susie.smith@example.com","login":{"uuid":"a9d0df26-405d-4db3-b193-2afcead1b5c4","username":"orangeleopard275","password":"trinidad","salt":"BajtPaEE","md5":"9a9d698a8e935ec011bc988fea0d89b8","sha1":"852ba8dceae7f20de214038654e1c301541235df","sha256":"004386a96adf6884d665ba622adba7c33ee54f38363162884ac723dc9b63269d"},"dob":{"date":"1989-12-25T04:52:46.766Z","age":31},"registered":{"date":"2008-04-28T00:25:03.621Z","age":12},"phone":"041-985-9510","cell":"081-478-5646","id":{"name":"PPS","value":"5917409T"},"picture":{"large":"https://randomuser.me/api/portraits/women/42.jpg","medium":"https://randomuser.me/api/portraits/med/women/42.jpg","thumbnail":"https://randomuser.me/api/portraits/thumb/women/42.jpg"},"nat":"IE"},{"gender":"male","name":{"title":"Mr","first":"Hermann Josef","last":"Brill"},"location":{"street":{"number":6078,"name":"Kastanienweg"},"city":"Harzgerode","state":"Berlin","country":"Germany","postcode":13072,"coordinates":{"latitude":"30.8628","longitude":"-51.5189"},"timezone":{"offset":"+1:00","description":"Brussels, Copenhagen, Madrid, Paris"}},"email":"hermannjosef.brill@example.com","login":{"uuid":"aa0dd743-2f2f-40d3-9f71-da244c2341fd","username":"whiteleopard177","password":"havefun","salt":"00kuNgNz","md5":"9fb86db757f2e0314d67e867e0b16368","sha1":"c5b025564a714254f157e6291deecd61a1c8cec0","sha256":"96baa369f05a9bbe89185023297a53d5368a2cec37cd9e2d4a17832c104c9e19"},"dob":{"date":"1966-02-02T04:04:38.355Z","age":54},"registered":{"date":"2007-04-29T23:12:18.893Z","age":13},"phone":"0025-3364449","cell":"0171-2488335","id":{"name":"","value":null},"picture":{"large":"https://randomuser.me/api/portraits/men/23.jpg","medium":"https://randomuser.me/api/portraits/med/men/23.jpg","thumbnail":"https://randomuser.me/api/portraits/thumb/men/23.jpg"},"nat":"DE"},{"gender":"male","name":{"title":"Mr","first":"Gamaliel","last":"Rocha"},"location":{"street":{"number":3785,"name":"Rua Amazonas "},"city":"Brasília","state":"Alagoas","country":"Brazil","postcode":81267,"coordinates":{"latitude":"86.9892","longitude":"-8.9788"},"timezone":{"offset":"-12:00","description":"Eniwetok, Kwajalein"}},"email":"gamaliel.rocha@example.com","login":{"uuid":"116f9e40-90ef-4455-bb0e-4855f73beb6c","username":"blacklion580","password":"beacon","salt":"J6iSmBJ3","md5":"65c2b9b54c447e9828ca91dc8255d759","sha1":"f42acdbfd7012898bcba45aa1f011502a90ce1b8","sha256":"91befe4c93ca57aedd81c19557ecdba847779f44d36a5a9e6d3730615821c2ef"},"dob":{"date":"1960-05-03T03:03:17.214Z","age":60},"registered":{"date":"2011-01-30T16:10:10.848Z","age":9},"phone":"(69) 9709-3550","cell":"(54) 0618-1389","id":{"name":"","value":null},"picture":{"large":"https://randomuser.me/api/portraits/men/64.jpg","medium":"https://randomuser.me/api/portraits/med/men/64.jpg","thumbnail":"https://randomuser.me/api/portraits/thumb/men/64.jpg"},"nat":"BR"},{"gender":"male","name":{"title":"Mr","first":"Fatih","last":"Numanoğlu"},"location":{"street":{"number":1902,"name":"Tunalı Hilmi Cd"},"city":"Karaman","state":"Gaziantep","country":"Turkey","postcode":96830,"coordinates":{"latitude":"-86.1586","longitude":"118.4020"},"timezone":{"offset":"+4:30","description":"Kabul"}},"email":"fatih.numanoglu@example.com","login":{"uuid":"db4fe900-91e4-4751-bedf-c7606310e0b4","username":"organicpanda615","password":"squerting","salt":"A6DNd7TC","md5":"5f778b91ce5061a53aab012fe848c1a5","sha1":"185638013cbbef11f249f934b98213b36dbc67f2","sha256":"15a4f5628e19eef345c48c03f84cdef3be362ac86cdb10468658d007f00ba0ca"},"dob":{"date":"1971-07-22T02:04:08.009Z","age":49},"registered":{"date":"2014-01-18T04:25:17.191Z","age":6},"phone":"(129)-347-4451","cell":"(230)-110-1729","id":{"name":"","value":null},"picture":{"large":"https://randomuser.me/api/portraits/men/19.jpg","medium":"https://randomuser.me/api/portraits/med/men/19.jpg","thumbnail":"https://randomuser.me/api/portraits/thumb/men/19.jpg"},"nat":"TR"},{"gender":"female","name":{"title":"Mrs","first":"آوینا","last":"احمدی"},"location":{"street":{"number":1188,"name":"خالد اسلامبولی"},"city":"آبادان","state":"آذربایجان شرقی","country":"Iran","postcode":43987,"coordinates":{"latitude":"-73.4964","longitude":"124.8000"},"timezone":{"offset":"-10:00","description":"Hawaii"}},"email":"awyn.hmdy@example.com","login":{"uuid":"d220a925-c4f3-488e-a8a3-2d627fa0d077","username":"beautifulswan278","password":"cannabis","salt":"DH2wqVeG","md5":"878044eb9ebf1fa271a3f4c3a3d325a1","sha1":"2b6f0c58257a1e090ac1503dc559655d82d2aa14","sha256":"16eb6a911c7c073848dd690edf47e0eeb2e9d10089ede9a32161839418ba9539"},"dob":{"date":"1962-01-24T12:13:21.141Z","age":58},"registered":{"date":"2010-04-04T04:13:10.147Z","age":10},"phone":"096-35305880","cell":"0914-737-3662","id":{"name":"","value":null},"picture":{"large":"https://randomuser.me/api/portraits/women/40.jpg","medium":"https://randomuser.me/api/portraits/med/women/40.jpg","thumbnail":"https://randomuser.me/api/portraits/thumb/women/40.jpg"},"nat":"IR"},{"gender":"male","name":{"title":"Mr","first":"Simon","last":"Sørensen"},"location":{"street":{"number":5735,"name":"Engsvinget"},"city":"Hammel","state":"Nordjylland","country":"Denmark","postcode":97403,"coordinates":{"latitude":"17.5149","longitude":"-110.3789"},"timezone":{"offset":"+3:00","description":"Baghdad, Riyadh, Moscow, St. Petersburg"}},"email":"simon.sorensen@example.com","login":{"uuid":"e324f019-dd3a-4911-be3d-5af4ba8e6a7c","username":"tinykoala163","password":"f**k","salt":"THAggt9V","md5":"84ab0eea91e09d44163e2f503a3fbdab","sha1":"b989f89be849a529a1f4927ea7071ee0933c4c11","sha256":"0a153bc51f2e18826a04c98d1c5f1aa571ef20840565d0433681c2410d82efd2"},"dob":{"date":"1949-09-17T08:31:25.027Z","age":71},"registered":{"date":"2019-05-28T18:12:47.206Z","age":1},"phone":"08253367","cell":"92279804","id":{"name":"CPR","value":"170949-4333"},"picture":{"large":"https://randomuser.me/api/portraits/men/82.jpg","medium":"https://randomuser.me/api/portraits/med/men/82.jpg","thumbnail":"https://randomuser.me/api/portraits/thumb/men/82.jpg"},"nat":"DK"},{"gender":"female","name":{"title":"Mrs","first":"Astrid","last":"Kristensen"},"location":{"street":{"number":9680,"name":"Morelvej"},"city":"Samsø","state":"Midtjylland","country":"Denmark","postcode":56779,"coordinates":{"latitude":"-60.4698","longitude":"-97.0413"},"timezone":{"offset":"+9:30","description":"Adelaide, Darwin"}},"email":"astrid.kristensen@example.com","login":{"uuid":"f9700449-b4f0-4b6e-bafb-13f2598bdbaa","username":"greenwolf763","password":"ginger1","salt":"EzNkDdPL","md5":"70f1076d18b7db9fa56382d45c54ad58","sha1":"0d41b5324663b0c1dc302f391ddb5fe1b16bc564","sha256":"8cb00c98f05968be9e304de4dfedea829812b7b986dbad1164162af028321e3b"},"dob":{"date":"1965-02-18T18:26:48.802Z","age":55},"registered":{"date":"2002-10-01T15:41:12.844Z","age":18},"phone":"48386332","cell":"79992023","id":{"name":"CPR","value":"180265-2282"},"picture":{"large":"https://randomuser.me/api/portraits/women/17.jpg","medium":"https://randomuser.me/api/portraits/med/women/17.jpg","thumbnail":"https://randomuser.me/api/portraits/thumb/women/17.jpg"},"nat":"DK"},{"gender":"female","name":{"title":"Ms","first":"Caitlin","last":"Brown"},"location":{"street":{"number":1975,"name":"Buckleys Road"},"city":"Timaru","state":"Southland","country":"New Zealand","postcode":52217,"coordinates":{"latitude":"-53.9539","longitude":"-20.9721"},"timezone":{"offset":"+9:00","description":"Tokyo, Seoul, Osaka, Sapporo, Yakutsk"}},"email":"caitlin.brown@example.com","login":{"uuid":"f865becf-8d15-4e97-847e-942ad471ea39","username":"silverkoala237","password":"charlie1","salt":"kNTpLDcC","md5":"3a1ff582f09dedbf28526d11293915a6","sha1":"a8387f002aadc0d9dd6c2ad161160c9455f0e27e","sha256":"6b6ba263e90d59d3f66d6c11c6ba9c25cf307647c9066b2ea0235d9c9bcecce8"},"dob":{"date":"1978-07-08T16:03:11.313Z","age":42},"registered":{"date":"2019-07-17T15:44:33.976Z","age":1},"phone":"(192)-121-8790","cell":"(096)-751-2661","id":{"name":"","value":null},"picture":{"large":"https://randomuser.me/api/portraits/women/16.jpg","medium":"https://randomuser.me/api/portraits/med/women/16.jpg","thumbnail":"https://randomuser.me/api/portraits/thumb/women/16.jpg"},"nat":"NZ"},{"gender":"male","name":{"title":"Mr","first":"Timmothy","last":"Peters"},"location":{"street":{"number":4251,"name":"North Road"},"city":"Donabate","state":"Meath","country":"Ireland","postcode":12898,"coordinates":{"latitude":"-40.9868","longitude":"-96.9914"},"timezone":{"offset":"+5:30","description":"Bombay, Calcutta, Madras, New Delhi"}},"email":"timmothy.peters@example.com","login":{"uuid":"4f655140-b8f3-4610-b00a-bc1eed2ff7f5","username":"bigmouse628","password":"sawyer","salt":"eeuiOOIG","md5":"2f7e27f24b2df6ccebe3edfb4a6916aa","sha1":"5536da92fa3a63054fabc7a36233f05907fb42b9","sha256":"9670eeb71ef1ac7bd21338efd4cc8b7a1bdfb97acd671d2126fa4e198eca955c"},"dob":{"date":"1987-12-31T14:20:43.898Z","age":33},"registered":{"date":"2011-01-20T07:03:44.153Z","age":9},"phone":"071-615-4242","cell":"081-406-6184","id":{"name":"PPS","value":"1241934T"},"picture":{"large":"https://randomuser.me/api/portraits/men/35.jpg","medium":"https://randomuser.me/api/portraits/med/men/35.jpg","thumbnail":"https://randomuser.me/api/portraits/thumb/men/35.jpg"},"nat":"IE"},{"gender":"male","name":{"title":"Mr","first":"Berkant","last":"Van Alem"},"location":{"street":{"number":3250,"name":"Hertogenhof"},"city":"Boornzwaag","state":"Groningen","country":"Netherlands","postcode":93212,"coordinates":{"latitude":"-16.5700","longitude":"158.3386"},"timezone":{"offset":"+6:00","description":"Almaty, Dhaka, Colombo"}},"email":"berkant.vanalem@example.com","login":{"uuid":"58439b5c-2db3-43bc-bbe4-7a17498cdad5","username":"beautifulmouse274","password":"albert","salt":"vObvoKfz","md5":"921539045adc9938f3c446a0d97a8f98","sha1":"14c7a52c21773ab149fb48fc7fdb6e35bfc4e07e","sha256":"bba03760c15ea2989475bb7070f354df5bae2f55d38a2046d9ceec107f4cfb75"},"dob":{"date":"1987-03-11T14:07:43.995Z","age":33},"registered":{"date":"2010-08-09T00:49:47.990Z","age":10},"phone":"(583)-721-4296","cell":"(326)-067-1310","id":{"name":"BSN","value":"58680041"},"picture":{"large":"https://randomuser.me/api/portraits/men/28.jpg","medium":"https://randomuser.me/api/portraits/med/men/28.jpg","thumbnail":"https://randomuser.me/api/portraits/thumb/men/28.jpg"},"nat":"NL"},{"gender":"female","name":{"title":"Mrs","first":"Gabriele","last":"Kluth"},"location":{"street":{"number":9604,"name":"Feldstraße"},"city":"Datteln","state":"Sachsen-Anhalt","country":"Germany","postcode":79403,"coordinates":{"latitude":"-83.9762","longitude":"52.5351"},"timezone":{"offset":"+5:30","description":"Bombay, Calcutta, Madras, New Delhi"}},"email":"gabriele.kluth@example.com","login":{"uuid":"2bd26c3b-61fb-442a-bc77-fdf0915e8d6d","username":"brownbear526","password":"marvel","salt":"FtR7GOS2","md5":"c7d8f6f3320539198c797ef35b0d4e0f","sha1":"7ba6bdbd4d96ee3cb866691aee7c189591f02efb","sha256":"3fb4084ba499c081f90e1e969dce31a21c5e4fd07b20a7a9c06f47452834f4bc"},"dob":{"date":"1949-09-29T10:38:41.339Z","age":71},"registered":{"date":"2008-03-20T11:36:33.042Z","age":12},"phone":"0856-0021667","cell":"0172-3207750","id":{"name":"","value":null},"picture":{"large":"https://randomuser.me/api/portraits/women/40.jpg","medium":"https://randomuser.me/api/portraits/med/women/40.jpg","thumbnail":"https://randomuser.me/api/portraits/thumb/women/40.jpg"},"nat":"DE"},{"gender":"female","name":{"title":"Ms","first":"الینا","last":"حسینی"},"location":{"street":{"number":721,"name":"هویزه"},"city":"همدان","state":"لرستان","country":"Iran","postcode":29608,"coordinates":{"latitude":"-26.7589","longitude":"-149.8375"},"timezone":{"offset":"-4:00","description":"Atlantic Time (Canada), Caracas, La Paz"}},"email":"lyn.hsyny@example.com","login":{"uuid":"3ed2ef32-70e0-4f89-92e6-834656f0fb1f","username":"redbutterfly117","password":"engage","salt":"gWW9fXTU","md5":"84f394e5dd4468f7d660a17da74f574f","sha1":"e6bfae0d7b54b56fd5856ce385a6dce6b7734422","sha256":"3b851ce9891c431d1710317156b286e23719af4ccfaf9842760127ff6e9d199f"},"dob":{"date":"1981-04-18T07:46:06.981Z","age":39},"registered":{"date":"2003-04-12T23:18:54.046Z","age":17},"phone":"081-08498219","cell":"0901-500-2526","id":{"name":"","value":null},"picture":{"large":"https://randomuser.me/api/portraits/women/26.jpg","medium":"https://randomuser.me/api/portraits/med/women/26.jpg","thumbnail":"https://randomuser.me/api/portraits/thumb/women/26.jpg"},"nat":"IR"},{"gender":"male","name":{"title":"Mr","first":"Idavide","last":"Ferreira"},"location":{"street":{"number":8075,"name":"Rua Santo Antônio "},"city":"Linhares","state":"Alagoas","country":"Brazil","postcode":21734,"coordinates":{"latitude":"-31.9375","longitude":"15.3751"},"timezone":{"offset":"0:00","description":"Western Europe Time, London, Lisbon, Casablanca"}},"email":"idavide.ferreira@example.com","login":{"uuid":"038612a4-8f12-4f19-bc29-bedd61ba1b70","username":"whitefish773","password":"rhonda","salt":"1s7fq21K","md5":"a1c09b50b28ee07f726ddd12c10f770b","sha1":"8638c499622c40a5ecfe8a2f564ccfe788e6478a","sha256":"cae5d9429607664bf1ddd4cc536bf53047765ae832e01eb234110dd53add7c7e"},"dob":{"date":"1946-05-07T02:05:47.459Z","age":74},"registered":{"date":"2016-07-01T02:03:41.842Z","age":4},"phone":"(37) 8739-7969","cell":"(43) 9020-0511","id":{"name":"","value":null},"picture":{"large":"https://randomuser.me/api/portraits/men/96.jpg","medium":"https://randomuser.me/api/portraits/med/men/96.jpg","thumbnail":"https://randomuser.me/api/portraits/thumb/men/96.jpg"},"nat":"BR"},{"gender":"male","name":{"title":"Mr","first":"Ronnie","last":"Washington"},"location":{"street":{"number":4840,"name":"Karen Dr"},"city":"Melbourne","state":"Western Australia","country":"Australia","postcode":6951,"coordinates":{"latitude":"-62.1114","longitude":"-66.2915"},"timezone":{"offset":"-1:00","description":"Azores, Cape Verde Islands"}},"email":"ronnie.washington@example.com","login":{"uuid":"a077e883-d578-4fd8-a811-6cc8a7a8e1b7","username":"angrypeacock238","password":"simon1","salt":"ADBTNzu3","md5":"2ada1fff13c3dff053298dc2f594bd0e","sha1":"7bddb25faba8d91b77dd875263bc140812772e73","sha256":"94052fe696fb0cad3253a70356d51e513ce43eb4bec3c6ec1983f9b6a193de25"},"dob":{"date":"1956-06-14T22:13:40.611Z","age":64},"registered":{"date":"2011-02-16T04:34:48.556Z","age":9},"phone":"07-2997-4663","cell":"0491-800-309","id":{"name":"TFN","value":"444406835"},"picture":{"large":"https://randomuser.me/api/portraits/men/63.jpg","medium":"https://randomuser.me/api/portraits/med/men/63.jpg","thumbnail":"https://randomuser.me/api/portraits/thumb/men/63.jpg"},"nat":"AU"},{"gender":"male","name":{"title":"Monsieur","first":"Jean-Jacques","last":"Jean"},"location":{"street":{"number":9110,"name":"Rue de L'Abbé-Carton"},"city":"Saint-Maurice","state":"Ticino","country":"Switzerland","postcode":5084,"coordinates":{"latitude":"-85.4042","longitude":"163.2208"},"timezone":{"offset":"+7:00","description":"Bangkok, Hanoi, Jakarta"}},"email":"jean-jacques.jean@example.com","login":{"uuid":"44717975-20ff-425a-9a66-f8164303864a","username":"yellowsnake258","password":"camp","salt":"CelTmN2f","md5":"df8f16850f276e338ffbc174ef03ee03","sha1":"229881a8edbddb20f55119bbbcfe946960fa56fa","sha256":"8b7e4f6dbd1388ba3b7d5acdce32874e57fc8caebeb1df48c0feb2cff5fe1dd6"},"dob":{"date":"1961-06-18T15:19:37.640Z","age":59},"registered":{"date":"2005-01-22T22:03:59.023Z","age":15},"phone":"077 304 21 57","cell":"078 109 88 95","id":{"name":"AVS","value":"756.1099.0679.59"},"picture":{"large":"https://randomuser.me/api/portraits/men/43.jpg","medium":"https://randomuser.me/api/portraits/med/men/43.jpg","thumbnail":"https://randomuser.me/api/portraits/thumb/men/43.jpg"},"nat":"CH"},{"gender":"female","name":{"title":"Ms","first":"Megan","last":"Gilbert"},"location":{"street":{"number":897,"name":"Wheeler Ridge Dr"},"city":"Bundaberg","state":"South Australia","country":"Australia","postcode":3955,"coordinates":{"latitude":"-14.4265","longitude":"-32.4533"},"timezone":{"offset":"+5:00","description":"Ekaterinburg, Islamabad, Karachi, Tashkent"}},"email":"megan.gilbert@example.com","login":{"uuid":"6f236dd5-4814-46d0-a120-c9e2b369e129","username":"smallkoala972","password":"kevin","salt":"v2hkR2ut","md5":"f43e16c03ccd465c02fb89432f9b31a9","sha1":"dda7a0f4c0eb343903bec60a1bddb9168075587a","sha256":"2d07450d88ad8cc174f7fa63e84d14bac18439746235c74780cf5f28ba7c8885"},"dob":{"date":"1977-04-27T05:49:35.246Z","age":43},"registered":{"date":"2006-03-06T15:00:53.128Z","age":14},"phone":"07-1616-7600","cell":"0454-654-170","id":{"name":"TFN","value":"338055404"},"picture":{"large":"https://randomuser.me/api/portraits/women/5.jpg","medium":"https://randomuser.me/api/portraits/med/women/5.jpg","thumbnail":"https://randomuser.me/api/portraits/thumb/women/5.jpg"},"nat":"AU"},{"gender":"female","name":{"title":"Mrs","first":"Selma","last":"Nielsen"},"location":{"street":{"number":8953,"name":"Marsvej"},"city":"København V","state":"Syddanmark","country":"Denmark","postcode":29098,"coordinates":{"latitude":"6.0716","longitude":"-75.6142"},"timezone":{"offset":"+7:00","description":"Bangkok, Hanoi, Jakarta"}},"email":"selma.nielsen@example.com","login":{"uuid":"8a9feb1f-5980-4961-a2e2-5dfe26aa3ad5","username":"angrypanda413","password":"whistler","salt":"kUFl4Mon","md5":"6e224276b8d3d7e0a98a6b0f50c88d61","sha1":"670af6099281232f9f232707d47959b3bec99c70","sha256":"e361c20b03d46a19da022b45a815c9086ea23675d42e825fb52b54c118a7b431"},"dob":{"date":"1991-01-18T12:26:18.788Z","age":29},"registered":{"date":"2007-07-02T15:23:37.344Z","age":13},"phone":"91570323","cell":"32202461","id":{"name":"CPR","value":"180191-1320"},"picture":{"large":"https://randomuser.me/api/portraits/women/37.jpg","medium":"https://randomuser.me/api/portraits/med/women/37.jpg","thumbnail":"https://randomuser.me/api/portraits/thumb/women/37.jpg"},"nat":"DK"},{"gender":"female","name":{"title":"Mrs","first":"Loni","last":"Willms"},"location":{"street":{"number":7476,"name":"Uhlandstraße"},"city":"Münstermaifeld","state":"Niedersachsen","country":"Germany","postcode":53522,"coordinates":{"latitude":"83.6608","longitude":"-26.4406"},"timezone":{"offset":"-9:00","description":"Alaska"}},"email":"loni.willms@example.com","login":{"uuid":"e7a0fb7d-9b97-4a33-8f47-c77824501312","username":"beautifulleopard465","password":"juan","salt":"j5X3cykJ","md5":"0087f65cae718c42387b3ed318070c5b","sha1":"81992530e5a7d3550faae0c8dd5df148a4dd773a","sha256":"256329b5fbad8e7f8023a4c032b6faa3703c93e1191f4eeafef9464730dcd8ce"},"dob":{"date":"1992-05-25T08:16:47.432Z","age":28},"registered":{"date":"2013-01-09T12:14:14.480Z","age":7},"phone":"0301-6331332","cell":"0174-4091924","id":{"name":"","value":null},"picture":{"large":"https://randomuser.me/api/portraits/women/23.jpg","medium":"https://randomuser.me/api/portraits/med/women/23.jpg","thumbnail":"https://randomuser.me/api/portraits/thumb/women/23.jpg"},"nat":"DE"},{"gender":"male","name":{"title":"Mr","first":"Mustafa","last":"Tazegül"},"location":{"street":{"number":516,"name":"Talak Göktepe Cd"},"city":"Ağrı","state":"Kilis","country":"Turkey","postcode":74537,"coordinates":{"latitude":"46.4596","longitude":"-72.7071"},"timezone":{"offset":"-4:00","description":"Atlantic Time (Canada), Caracas, La Paz"}},"email":"mustafa.tazegul@example.com","login":{"uuid":"ea810a11-3006-478d-94c1-830d3576fa58","username":"brownmouse183","password":"yeah","salt":"N57db8yQ","md5":"a95858423593b627e80cf2b24c74cc23","sha1":"68ae9450eb910c93a537b1af6294f6606329c86a","sha256":"5b74931768f68c7d4dc2ccd278fda1a57c24d77f5be69930b50b83a0d84987fd"},"dob":{"date":"1974-03-28T02:45:41.727Z","age":46},"registered":{"date":"2006-01-07T15:07:39.260Z","age":14},"phone":"(386)-448-8193","cell":"(270)-149-3555","id":{"name":"","value":null},"picture":{"large":"https://randomuser.me/api/portraits/men/93.jpg","medium":"https://randomuser.me/api/portraits/med/men/93.jpg","thumbnail":"https://randomuser.me/api/portraits/thumb/men/93.jpg"},"nat":"TR"},{"gender":"male","name":{"title":"Mr","first":"Miguel","last":"Hopkins"},"location":{"street":{"number":1235,"name":"South Street"},"city":"Durham","state":"South Yorkshire","country":"United Kingdom","postcode":"E74 2LE","coordinates":{"latitude":"-33.1649","longitude":"-147.5247"},"timezone":{"offset":"+4:30","description":"Kabul"}},"email":"miguel.hopkins@example.com","login":{"uuid":"9ec026b5-c49a-4446-9f89-248fb86114fc","username":"smallkoala944","password":"rang","salt":"lagrz2gv","md5":"07bb9b7f27249430e1f5b34e2f497004","sha1":"059350bdbae4aaaac3b157540cee4b301ed04be0","sha256":"2c02aacd1ac7da1a5cb2614002f23003fcb1f8a3061676f61c34a769ca2e6e3e"},"dob":{"date":"1967-12-13T06:05:23.105Z","age":53},"registered":{"date":"2010-08-21T18:58:14.073Z","age":10},"phone":"0121 616 8649","cell":"0790-931-125","id":{"name":"NINO","value":"NA 80 36 74 P"},"picture":{"large":"https://randomuser.me/api/portraits/men/74.jpg","medium":"https://randomuser.me/api/portraits/med/men/74.jpg","thumbnail":"https://randomuser.me/api/portraits/thumb/men/74.jpg"},"nat":"GB"},{"gender":"female","name":{"title":"Ms","first":"Eva","last":"Ouellet"},"location":{"street":{"number":4493,"name":"Charles St"},"city":"Hampstead","state":"Saskatchewan","country":"Canada","postcode":"K0U 9G7","coordinates":{"latitude":"-28.8687","longitude":"142.4648"},"timezone":{"offset":"-3:00","description":"Brazil, Buenos Aires, Georgetown"}},"email":"eva.ouellet@example.com","login":{"uuid":"711fd0d4-865b-4bf4-bcfd-06765549257e","username":"goldenbear328","password":"durango","salt":"Zk1pFnI9","md5":"89b34f4bdc71a7c36a1d54b459fdc4ac","sha1":"170bccc473d3ff1e61bd83d7c0f00a3aa822c3f5","sha256":"f87c351133551b924513e9c6bd292477ee95721379034c6cf5994ebaf522a3f6"},"dob":{"date":"1984-05-10T07:16:28.707Z","age":36},"registered":{"date":"2002-08-08T14:26:49.235Z","age":18},"phone":"930-871-9405","cell":"122-732-0045","id":{"name":"","value":null},"picture":{"large":"https://randomuser.me/api/portraits/women/32.jpg","medium":"https://randomuser.me/api/portraits/med/women/32.jpg","thumbnail":"https://randomuser.me/api/portraits/thumb/women/32.jpg"},"nat":"CA"},{"gender":"female","name":{"title":"Mrs","first":"Andrine","last":"Engeset"},"location":{"street":{"number":7857,"name":"Persbråtan"},"city":"Tretten","state":"Oslo","country":"Norway","postcode":"6395","coordinates":{"latitude":"84.2469","longitude":"12.1747"},"timezone":{"offset":"+9:30","description":"Adelaide, Darwin"}},"email":"andrine.engeset@example.com","login":{"uuid":"b7876a27-0a96-45fb-a027-e5db654bffe4","username":"organiccat503","password":"snapple","salt":"dOkJnXjW","md5":"f23756f29fcd66ff7c4e4d528214df6f","sha1":"89cd0630a64ccc5dba5e2c1df7f36707b8f726d4","sha256":"263b5dc6993e4f11b021706bbb8b539e2133cee83b78f98dfda5c8d223c536a6"},"dob":{"date":"1970-09-05T13:11:39.027Z","age":50},"registered":{"date":"2015-08-25T13:21:09.140Z","age":5},"phone":"82339886","cell":"96498905","id":{"name":"FN","value":"05097027864"},"picture":{"large":"https://randomuser.me/api/portraits/women/37.jpg","medium":"https://randomuser.me/api/portraits/med/women/37.jpg","thumbnail":"https://randomuser.me/api/portraits/thumb/women/37.jpg"},"nat":"NO"},{"gender":"female","name":{"title":"Mrs","first":"Katherine","last":"Stephens"},"location":{"street":{"number":1736,"name":"King Street"},"city":"St Albans","state":"Highlands and Islands","country":"United Kingdom","postcode":"UO77 9RE","coordinates":{"latitude":"-72.1516","longitude":"-100.2173"},"timezone":{"offset":"-5:00","description":"Eastern Time (US & Canada), Bogota, Lima"}},"email":"katherine.stephens@example.com","login":{"uuid":"634e4e82-0bd3-41da-b2ab-397073c72af2","username":"bigtiger397","password":"dean","salt":"4idbnoSw","md5":"eb5cd552b2b13d9513102facbda3fd5f","sha1":"dd8e91b36203da6f2929f24ec1d371a68c6ab41a","sha256":"ae5fad33f1f1f62d132f34705a9cf745927dce5a063a2890529d3f81de0fdc20"},"dob":{"date":"1961-06-09T05:01:08.513Z","age":59},"registered":{"date":"2019-09-02T17:31:33.662Z","age":1},"phone":"015395 32247","cell":"0721-175-359","id":{"name":"NINO","value":"HM 33 55 19 S"},"picture":{"large":"https://randomuser.me/api/portraits/women/78.jpg","medium":"https://randomuser.me/api/portraits/med/women/78.jpg","thumbnail":"https://randomuser.me/api/portraits/thumb/women/78.jpg"},"nat":"GB"},{"gender":"female","name":{"title":"Miss","first":"Marie","last":"Hernandez"},"location":{"street":{"number":6503,"name":"Springfield Road"},"city":"Lincoln","state":"Gloucestershire","country":"United Kingdom","postcode":"JU6 8HH","coordinates":{"latitude":"-63.6944","longitude":"155.8582"},"timezone":{"offset":"+7:00","description":"Bangkok, Hanoi, Jakarta"}},"email":"marie.hernandez@example.com","login":{"uuid":"4232dbf1-0fab-4913-aa29-4ebb674a0115","username":"whiterabbit709","password":"skyline","salt":"2o8uhWDe","md5":"6d231c3c97c5c9d018a258e96fa130dc","sha1":"a1bc7cd2f7910fc007acbdc13730ed5786d46b0e","sha256":"5570442fa078c6c356204aa39bf60dadfe6420a961f643a7389bf1908d5b6e2f"},"dob":{"date":"1988-09-13T14:15:17.524Z","age":32},"registered":{"date":"2014-01-01T19:40:08.421Z","age":6},"phone":"015394 73829","cell":"0738-224-651","id":{"name":"NINO","value":"XW 95 84 17 I"},"picture":{"large":"https://randomuser.me/api/portraits/women/53.jpg","medium":"https://randomuser.me/api/portraits/med/women/53.jpg","thumbnail":"https://randomuser.me/api/portraits/thumb/women/53.jpg"},"nat":"GB"},{"gender":"male","name":{"title":"Mr","first":"Benjamin","last":"Roy"},"location":{"street":{"number":6381,"name":"Brock Rd"},"city":"Summerside","state":"Alberta","country":"Canada","postcode":"S1W 8M9","coordinates":{"latitude":"-66.5406","longitude":"55.8864"},"timezone":{"offset":"+3:30","description":"Tehran"}},"email":"benjamin.roy@example.com","login":{"uuid":"a88c199c-85ea-4286-8647-0aa1d62372f5","username":"whitetiger923","password":"wedding","salt":"AMhSwt24","md5":"f8a58b3920961925e9fe88b0f9344475","sha1":"22851bc50c4e9d91afa691a18f680f017ed63d61","sha256":"ea9686eede5af9f3bb18f61d260f51642f095ffc21a068b9edc2ada73bb50388"},"dob":{"date":"1965-08-30T21:06:23.477Z","age":55},"registered":{"date":"2015-06-17T12:20:17.727Z","age":5},"phone":"400-280-0815","cell":"921-483-1682","id":{"name":"","value":null},"picture":{"large":"https://randomuser.me/api/portraits/men/66.jpg","medium":"https://randomuser.me/api/portraits/med/men/66.jpg","thumbnail":"https://randomuser.me/api/portraits/thumb/men/66.jpg"},"nat":"CA"},{"gender":"male","name":{"title":"Mr","first":"Jakob","last":"Franklin"},"location":{"street":{"number":8570,"name":"Park Lane"},"city":"Leeds","state":"East Sussex","country":"United Kingdom","postcode":"H53 9SE","coordinates":{"latitude":"-14.7248","longitude":"84.2439"},"timezone":{"offset":"+9:30","description":"Adelaide, Darwin"}},"email":"jakob.franklin@example.com","login":{"uuid":"01bc5b15-e5a0-4539-9611-a3c748d5c326","username":"organicpanda429","password":"jjjjjj","salt":"5FL5RV3j","md5":"8caa2e9e799b69602ac462180d4f8d59","sha1":"7018dc093570bf987025d6141f73caa1ffc685db","sha256":"bfbc5d5afdb7c58d4689fb50136c7bca59ef9c651c305fc716115ce429be94a6"},"dob":{"date":"1963-08-09T05:59:49.126Z","age":57},"registered":{"date":"2013-03-26T05:38:56.388Z","age":7},"phone":"015242 57611","cell":"0750-472-956","id":{"name":"NINO","value":"KR 09 03 64 D"},"picture":{"large":"https://randomuser.me/api/portraits/men/67.jpg","medium":"https://randomuser.me/api/portraits/med/men/67.jpg","thumbnail":"https://randomuser.me/api/portraits/thumb/men/67.jpg"},"nat":"GB"},{"gender":"female","name":{"title":"Mrs","first":"Elizabeth","last":"Addy"},"location":{"street":{"number":4553,"name":"Grand Ave"},"city":"Southampton","state":"Nova Scotia","country":"Canada","postcode":"V7A 1K0","coordinates":{"latitude":"-52.5824","longitude":"172.3804"},"timezone":{"offset":"+9:30","description":"Adelaide, Darwin"}},"email":"elizabeth.addy@example.com","login":{"uuid":"a54a1ab2-6208-4ead-8171-3d57abf42dc8","username":"heavyswan149","password":"dontknow","salt":"39lUJw5N","md5":"29df18b2172009d93ce02318383b6bb1","sha1":"c9905c7164826a987e21b5ccc0545b0bf09ccf5c","sha256":"dc305cb050f0734139f7f22f15adbc1f307d28c54d3cd21fd22a34f4ecf40dfc"},"dob":{"date":"1953-07-31T19:10:48.199Z","age":67},"registered":{"date":"2007-11-16T01:21:54.862Z","age":13},"phone":"855-190-2910","cell":"095-237-9600","id":{"name":"","value":null},"picture":{"large":"https://randomuser.me/api/portraits/women/7.jpg","medium":"https://randomuser.me/api/portraits/med/women/7.jpg","thumbnail":"https://randomuser.me/api/portraits/thumb/women/7.jpg"},"nat":"CA"},{"gender":"female","name":{"title":"Miss","first":"Joanne","last":"Edwards"},"location":{"street":{"number":4469,"name":"E Sandy Lake Rd"},"city":"Odessa","state":"Tennessee","country":"United States","postcode":12125,"coordinates":{"latitude":"-34.2589","longitude":"72.5458"},"timezone":{"offset":"+3:30","description":"Tehran"}},"email":"joanne.edwards@example.com","login":{"uuid":"f8abd940-7156-4d8a-8032-aac4531bb80a","username":"bigladybug543","password":"jughead","salt":"e1NH28b7","md5":"2c99eac3c3bde46e0e579d11caf0bc5b","sha1":"d94357b161ee9a7ea4d7e5284284f64fb95bc388","sha256":"65d38aedbee2b0b0839c0fd5ca922bf9a3d660075ca0f6bf893ef629332b1464"},"dob":{"date":"1946-07-25T07:23:28.739Z","age":74},"registered":{"date":"2003-12-04T13:45:23.915Z","age":17},"phone":"(673)-874-1518","cell":"(031)-012-7488","id":{"name":"SSN","value":"561-09-6723"},"picture":{"large":"https://randomuser.me/api/portraits/women/62.jpg","medium":"https://randomuser.me/api/portraits/med/women/62.jpg","thumbnail":"https://randomuser.me/api/portraits/thumb/women/62.jpg"},"nat":"US"},{"gender":"male","name":{"title":"Mr","first":"Steve","last":"Ryan"},"location":{"street":{"number":8717,"name":"Cherry St"},"city":"Australian Capital Territory","state":"Australian Capital Territory","country":"Australia","postcode":6576,"coordinates":{"latitude":"18.6697","longitude":"-114.2903"},"timezone":{"offset":"+4:30","description":"Kabul"}},"email":"steve.ryan@example.com","login":{"uuid":"1d41dd93-1ccf-41cb-85b1-0a04d20d7fe3","username":"yellowelephant432","password":"cambridg","salt":"wbJ4JlP6","md5":"939e2d509ab9d85f38a881c580305a02","sha1":"09f0fa9d00b822d8559ac0142884ca37e214f38f","sha256":"b158878e176b7fca7cefb8184da68240d36492af6a8bd8580064ce8fa1aa2f77"},"dob":{"date":"1954-01-07T11:53:02.940Z","age":66},"registered":{"date":"2009-03-27T03:55:26.859Z","age":11},"phone":"06-2868-3301","cell":"0462-746-740","id":{"name":"TFN","value":"657762613"},"picture":{"large":"https://randomuser.me/api/portraits/men/25.jpg","medium":"https://randomuser.me/api/portraits/med/men/25.jpg","thumbnail":"https://randomuser.me/api/portraits/thumb/men/25.jpg"},"nat":"AU"},{"gender":"male","name":{"title":"Mr","first":"Vincent","last":"Patel"},"location":{"street":{"number":8643,"name":"Domain Road"},"city":"Upper Hutt","state":"Gisborne","country":"New Zealand","postcode":67135,"coordinates":{"latitude":"-64.2576","longitude":"168.9627"},"timezone":{"offset":"+9:30","description":"Adelaide, Darwin"}},"email":"vincent.patel@example.com","login":{"uuid":"02800383-9177-476c-a712-d4f14dd9ce4b","username":"smallleopard302","password":"pressure","salt":"6PMMIc8y","md5":"4587ce1f447433ff6969a9eadf050489","sha1":"c54415aca396d6d130635b15a6e77673eb328535","sha256":"0c693003197f90d54acb03e73c92cbee12e3c2dbe84233bf74b1ea0796fc21d8"},"dob":{"date":"1985-10-10T10:57:21.042Z","age":35},"registered":{"date":"2017-06-04T00:17:13.398Z","age":3},"phone":"(993)-881-3922","cell":"(732)-031-9313","id":{"name":"","value":null},"picture":{"large":"https://randomuser.me/api/portraits/men/21.jpg","medium":"https://randomuser.me/api/portraits/med/men/21.jpg","thumbnail":"https://randomuser.me/api/portraits/thumb/men/21.jpg"},"nat":"NZ"},{"gender":"male","name":{"title":"Mr","first":"Benjamin","last":"Thomsen"},"location":{"street":{"number":7160,"name":"Lyngtoften"},"city":"Lundby","state":"Sjælland","country":"Denmark","postcode":32197,"coordinates":{"latitude":"-84.3580","longitude":"113.4977"},"timezone":{"offset":"+3:30","description":"Tehran"}},"email":"benjamin.thomsen@example.com","login":{"uuid":"f5cdb6fb-faf6-46e0-8009-2105df6769f5","username":"beautifulbear460","password":"superman","salt":"fJccpT9q","md5":"3bfe1f5a688bf860e6bfd5e620af679b","sha1":"81955994bdb683c2a68c1b8bea408d789d9f9d07","sha256":"8c7d6b04555cf25052a2c4080455d2d33104c0a368af1050410f99f2802f0e48"},"dob":{"date":"1983-06-05T21:13:26.064Z","age":37},"registered":{"date":"2008-07-29T07:44:48.315Z","age":12},"phone":"31289359","cell":"61820923","id":{"name":"CPR","value":"050683-8996"},"picture":{"large":"https://randomuser.me/api/portraits/men/72.jpg","medium":"https://randomuser.me/api/portraits/med/men/72.jpg","thumbnail":"https://randomuser.me/api/portraits/thumb/men/72.jpg"},"nat":"DK"},{"gender":"female","name":{"title":"Ms","first":"Katrine","last":"Johansen"},"location":{"street":{"number":1095,"name":"Vordingborgvej"},"city":"Assens","state":"Hovedstaden","country":"Denmark","postcode":33266,"coordinates":{"latitude":"-12.7769","longitude":"-10.8121"},"timezone":{"offset":"0:00","description":"Western Europe Time, London, Lisbon, Casablanca"}},"email":"katrine.johansen@example.com","login":{"uuid":"7ba65ed0-b238-4ab3-afb6-ab6e2d0140e7","username":"silversnake830","password":"adriana","salt":"kFtBl0d1","md5":"0f3fca03de2f6a4257303b75ec997b84","sha1":"7ef171ff37ae32eae148a0f5df72cfafba653a05","sha256":"2ce9eb94a9c86f0ddaf4a0ef4d101ad65d765e888bd038aab348135bf206222c"},"dob":{"date":"1953-11-15T22:55:51.995Z","age":67},"registered":{"date":"2015-04-29T14:43:16.254Z","age":5},"phone":"86491213","cell":"08410258","id":{"name":"CPR","value":"151153-2555"},"picture":{"large":"https://randomuser.me/api/portraits/women/69.jpg","medium":"https://randomuser.me/api/portraits/med/women/69.jpg","thumbnail":"https://randomuser.me/api/portraits/thumb/women/69.jpg"},"nat":"DK"},{"gender":"female","name":{"title":"Mademoiselle","first":"Elena","last":"Lambert"},"location":{"street":{"number":4862,"name":"Rue de la Gare"},"city":"Évilard","state":"Thurgau","country":"Switzerland","postcode":4557,"coordinates":{"latitude":"-12.8746","longitude":"-34.0268"},"timezone":{"offset":"-3:30","description":"Newfoundland"}},"email":"elena.lambert@example.com","login":{"uuid":"71ad68b3-177d-4e8c-8c71-3b3ad13fd242","username":"ticklishswan421","password":"alphabet","salt":"Tp1J80I4","md5":"d708745d24422129833f19416a1c450e","sha1":"457bc4e29b517c1bea594650da66d9b0e6587da3","sha256":"a6a3ce4f7b2a9a29e260cee967013c99be73dc273cdf459aa7612e9a4977858b"},"dob":{"date":"1979-10-10T19:14:22.105Z","age":41},"registered":{"date":"2004-11-03T12:10:48.049Z","age":16},"phone":"076 886 23 25","cell":"077 865 75 14","id":{"name":"AVS","value":"756.8093.3818.72"},"picture":{"large":"https://randomuser.me/api/portraits/women/80.jpg","medium":"https://randomuser.me/api/portraits/med/women/80.jpg","thumbnail":"https://randomuser.me/api/portraits/thumb/women/80.jpg"},"nat":"CH"},{"gender":"male","name":{"title":"Mr","first":"Marion","last":"Castro"},"location":{"street":{"number":2700,"name":"Eason Rd"},"city":"Tweed","state":"Queensland","country":"Australia","postcode":9113,"coordinates":{"latitude":"-11.7909","longitude":"-16.6118"},"timezone":{"offset":"-5:00","description":"Eastern Time (US & Canada), Bogota, Lima"}},"email":"marion.castro@example.com","login":{"uuid":"8506428b-b10f-4edf-810e-f09be9f09a4e","username":"whiteduck809","password":"sword","salt":"cSwQjo4r","md5":"23f5c06ddd1bc80e33296560275d6e2c","sha1":"a257eb38c35a4ad5116ff2582afef4c1080fd8b9","sha256":"69290a0a52c9457494571f52491ead2a6b36e002f3238d222ef14f29710481c4"},"dob":{"date":"1958-05-02T03:19:40.135Z","age":62},"registered":{"date":"2006-01-08T00:47:32.579Z","age":14},"phone":"04-9827-0212","cell":"0496-574-366","id":{"name":"TFN","value":"230654339"},"picture":{"large":"https://randomuser.me/api/portraits/men/11.jpg","medium":"https://randomuser.me/api/portraits/med/men/11.jpg","thumbnail":"https://randomuser.me/api/portraits/thumb/men/11.jpg"},"nat":"AU"},{"gender":"female","name":{"title":"Miss","first":"Julia","last":"Diez"},"location":{"street":{"number":9653,"name":"Calle de Toledo"},"city":"Parla","state":"Navarra","country":"Spain","postcode":73377,"coordinates":{"latitude":"32.0160","longitude":"-147.7291"},"timezone":{"offset":"+4:00","description":"Abu Dhabi, Muscat, Baku, Tbilisi"}},"email":"julia.diez@example.com","login":{"uuid":"f38b5d22-bd55-48c7-b930-b2919ca1197a","username":"silvermouse301","password":"bummer","salt":"Hj7DcNEy","md5":"0fab390a75699131ea9d68e180ede021","sha1":"c89f079e635af6d8cdec4005d673608b65452f0c","sha256":"038a5500644d378d23b89bdd76c96e7b574609425faea94061d8db2c6fceb6ec"},"dob":{"date":"1979-04-24T20:42:35.413Z","age":41},"registered":{"date":"2009-09-09T10:54:11.751Z","age":11},"phone":"964-013-608","cell":"634-430-004","id":{"name":"DNI","value":"30248888-F"},"picture":{"large":"https://randomuser.me/api/portraits/women/28.jpg","medium":"https://randomuser.me/api/portraits/med/women/28.jpg","thumbnail":"https://randomuser.me/api/portraits/thumb/women/28.jpg"},"nat":"ES"},{"gender":"male","name":{"title":"Mr","first":"Thieu","last":"Hols"},"location":{"street":{"number":8016,"name":"Belmolendijk"},"city":"Budel-Dorplein","state":"Utrecht","country":"Netherlands","postcode":43977,"coordinates":{"latitude":"10.8847","longitude":"-13.1280"},"timezone":{"offset":"-3:30","description":"Newfoundland"}},"email":"thieu.hols@example.com","login":{"uuid":"2b055d09-8707-465c-998c-e87d32b82e93","username":"whiteduck665","password":"volcano","salt":"pEq9ERct","md5":"e8b6e8055c7f24aee49f523b2a0525d2","sha1":"af0dec5e3bc4f2ef1df23c1b69c8d56874bd9d23","sha256":"26012471932ad00b607293d862f8ee6fcc34820d25b5d339f1a4667a0823bb2f"},"dob":{"date":"1961-06-07T06:07:19.111Z","age":59},"registered":{"date":"2005-09-17T20:53:37.143Z","age":15},"phone":"(808)-307-3291","cell":"(115)-199-9642","id":{"name":"BSN","value":"41200206"},"picture":{"large":"https://randomuser.me/api/portraits/men/51.jpg","medium":"https://randomuser.me/api/portraits/med/men/51.jpg","thumbnail":"https://randomuser.me/api/portraits/thumb/men/51.jpg"},"nat":"NL"},{"gender":"male","name":{"title":"Mr","first":"Tom","last":"Fernandez"},"location":{"street":{"number":5042,"name":"Rue de la Gare"},"city":"Vitry-sur-Seine","state":"Calvados","country":"France","postcode":13241,"coordinates":{"latitude":"-50.4177","longitude":"167.3972"},"timezone":{"offset":"0:00","description":"Western Europe Time, London, Lisbon, Casablanca"}},"email":"tom.fernandez@example.com","login":{"uuid":"0b5d46f2-8b15-4345-8304-7a21530399f6","username":"ticklishleopard961","password":"addison","salt":"NzXLZSVF","md5":"b54b651664c70bd599c3266d174bc65e","sha1":"ec7ededa6fd64623108000639476ed9942363fc3","sha256":"e7853f28a419c4b39dabc4c8b7730c9486bc2cf7a35ddd1bf7c659bdac49e342"},"dob":{"date":"1989-12-25T04:49:33.587Z","age":31},"registered":{"date":"2006-01-27T09:16:56.338Z","age":14},"phone":"02-78-57-01-53","cell":"06-10-25-16-27","id":{"name":"INSEE","value":"1NNaN22821110 53"},"picture":{"large":"https://randomuser.me/api/portraits/men/26.jpg","medium":"https://randomuser.me/api/portraits/med/men/26.jpg","thumbnail":"https://randomuser.me/api/portraits/thumb/men/26.jpg"},"nat":"FR"},{"gender":"female","name":{"title":"Miss","first":"Elisabeth","last":"Gunnerød"},"location":{"street":{"number":8478,"name":"Gamle Herregårdsvei"},"city":"Degernes","state":"Oppland","country":"Norway","postcode":"7651","coordinates":{"latitude":"-69.9459","longitude":"89.1332"},"timezone":{"offset":"-2:00","description":"Mid-Atlantic"}},"email":"elisabeth.gunnerod@example.com","login":{"uuid":"e9872ece-0629-4708-ae93-501b55156476","username":"brownduck162","password":"flicks","salt":"5GZUPbZx","md5":"0a026cb167713d29c87d0e5ad18be23a","sha1":"19ca9a80d5299eb3610ee95cc3d320566c341f3e","sha256":"189627a062098a9ca8d162b87f20eb6b08b67e454765bf75dddb737b6a4de866"},"dob":{"date":"1960-06-29T04:26:30.950Z","age":60},"registered":{"date":"2007-10-11T12:13:10.418Z","age":13},"phone":"73269420","cell":"44664384","id":{"name":"FN","value":"29066009678"},"picture":{"large":"https://randomuser.me/api/portraits/women/6.jpg","medium":"https://randomuser.me/api/portraits/med/women/6.jpg","thumbnail":"https://randomuser.me/api/portraits/thumb/women/6.jpg"},"nat":"NO"},{"gender":"female","name":{"title":"Mrs","first":"آوینا","last":"محمدخان"},"location":{"street":{"number":6035,"name":"شهید آرش مهر"},"city":"کاشان","state":"مرکزی","country":"Iran","postcode":92653,"coordinates":{"latitude":"-89.2934","longitude":"157.8653"},"timezone":{"offset":"-1:00","description":"Azores, Cape Verde Islands"}},"email":"awyn.mhmdkhn@example.com","login":{"uuid":"2f36e4ac-4040-4fba-af00-f6af4a183f4d","username":"yellowfrog337","password":"apple1","salt":"hb9I28cZ","md5":"bf209ccac8f45847131ca8edb7af6dbb","sha1":"f7fb1641f2ab43dfc8b5eb7c09aa93105184d56e","sha256":"322a0d0177a9d7ea7bda58ad15f7d4b6c481b81689a96172273b084d400d5c0a"},"dob":{"date":"1977-08-20T10:56:08.126Z","age":43},"registered":{"date":"2010-05-08T16:35:12.187Z","age":10},"phone":"048-31657000","cell":"0957-635-1377","id":{"name":"","value":null},"picture":{"large":"https://randomuser.me/api/portraits/women/36.jpg","medium":"https://randomuser.me/api/portraits/med/women/36.jpg","thumbnail":"https://randomuser.me/api/portraits/thumb/women/36.jpg"},"nat":"IR"}]